Assg4/mealy_zero_det/mealy_zero_det.v
module mealy_zero_det(
	output reg y_out,
	input x_in,clk,reset);
reg [1:0] state,next_state;
parameter S0 = 2'b00, S1 = 2'b01, S2 = 2'b10, S3 = 2'b11 ;
always@(posedge clk,negedge reset)
	if (reset==0) state <= S0;
	else state<=next_state;
	always @ (state, x_in)
	case (state)
		S0:
			if (x_in) next_state = S2; else next_state = S1;
		S1:
			if (x_in) next_state = S2; else next_state = S1;
		
		S2:
			if (x_in) next_state = S1; else next_state = S2;
	endcase
always @ (state, x_in)
	case (state)
		S0:
			y_out = 0;
		S1, S2: y_out = ~x_in;
	endcase
endmodule

Assg4/mealy_zero_det/mealy_zero_det_tb.v
module mealy_zero_det_tb();
wire t_y_out;
reg t_x_in,t_clock,t_reset;
  mealy_zero_det uut(t_y_out,t_x_in,t_clock,t_reset);
initial #200 $finish;
initial 
	begin 
		$dumpfile("dump.vcd");
		$dumpvars(1);
		t_clock = 0; 
		forever #5 t_clock = ~t_clock; 
	end
initial 
fork
	t_reset = 0;
	#2 t_reset = 1;
	#87 t_reset = 0;
	#89 t_reset = 1;
	#10 t_x_in = 1;
	#30 t_x_in = 0;
	#40 t_x_in = 1;
	#50 t_x_in = 0;
	#52 t_x_in = 1;
	#54 t_x_in = 0;
	#70 t_x_in = 1;
	#80 t_x_in = 1;
	#70 t_x_in = 0;
	#90 t_x_in = 1;
	#100 t_x_in = 0;
	#120 t_x_in = 1;
	#160 t_x_in = 0;
	#170 t_x_in = 1;
join
endmodule

Assg4/mealy_zero_det/simulation/modelsim/dump.vcd
$date
	Mon Nov 13 16:45:54 2023
$end
$version
	ModelSim Version 10.5b
$end
$timescale
	1ps
$end

$scope module mealy_zero_det_tb $end
$var wire 1 ! t_y_out $end
$var reg 1 " t_x_in $end
$var reg 1 # t_clock $end
$var reg 1 $ t_reset $end
$upscope $end
$enddefinitions $end
#0
$dumpvars
x"
0#
0$
0!
$end
#2
1$
#5
1#
x!
#10
1"
0#
1!
#15
1#
#20
0#
#25
1#
#30
0"
0#
0!
#35
1#
#40
1"
0#
1!
#45
1#
#50
0"
0#
0!
#52
1"
1!
#54
0"
0!
#55
1#
#60
0#
#65
1#
#70
1"
0"
0#
#75
1#
#80
1"
0#
1!
#85
1#
#87
0$
0!
#89
1$
#90
0#
#95
1#
1!
#100
0"
0#
0!
#105
1#
#110
0#
#115
1#
#120
1"
0#
1!
#125
1#
#130
0#
#135
1#
#140
0#
#145
1#
#150
0#
#155
1#
#160
0"
0#
0!
#165
1#
#170
1"
0#
1!
